regexbuilder/__init__.py
regexbuilder_py-1.0.0.dist-info/LICENSE
regexbuilder_py-1.0.0.dist-info/METADATA
regexbuilder_py-1.0.0.dist-info/WHEEL
regexbuilder_py-1.0.0.dist-info/top_level.txt
regexbuilder_py-1.0.0.dist-info/RECORD
