Metadata-Version: 2.1
Name: regexbuilder-py
Version: 1.0.0
Summary: A functional wrapper for RegEx in Python.
Author-email: Aarav Malani <aarav.malani@gmail.com>
Project-URL: Homepage, https://github.com/AaravMalani/regexbuilder
Project-URL: Bug Tracker, https://github.com/AaravMalani/regexbuilder/issues
Classifier: Programming Language :: Python :: 3
Classifier: License :: OSI Approved :: MIT License
Classifier: Operating System :: OS Independent
Requires-Python: >=3.6
License-File: LICENSE
